atro_pylog/__init__.py
atro_pylog/level.py
atro_pylog/logger_type.py
atro_pylog/opentelemetry_setup.py
atro_pylog/rich_setup.py
atro_pylog/settings.py
atro_pylog-0.4.0.dist-info/METADATA
atro_pylog-0.4.0.dist-info/WHEEL
atro_pylog-0.4.0.dist-info/RECORD
